{
    "Translation": "VI1934",
    "group": "CÁC SÁCH THƠ-VĂN",
    "BookName": "Gióp ",
    "BookNumber": 18,
    "Audio": [
        "\\Audio\\VI1934\\giop\\12.mp3",
        "\\Audio\\VI1934\\1-ms-nguyen-thi\\giop\\12.mp3"
    ],
    "Content": "\n\u003cdiv class=\"title\"\u003e\u003ch1\u003e12\u003c/h1\u003e\u003ch3\u003eGióp bắt lẽ những lời đáp của các bạn mình\u003c/h3\u003e\u003c/div\u003e\n\u003cspan class=\"verse giop_12_1\"\u003e \u003csup\u003e1\u003c/sup\u003e Gióp đáp lại rằng: \u003cbr/\u003e\u003c/span\u003e\n\u003cspan class=\"verse giop_12_2\"\u003e \u003csup\u003e2\u003c/sup\u003e Hẳn chi các ngươi thật là người, \u003cbr/\u003e Sự khôn ngoan sẽ đồng chết mất với các ngươi mà chớ! \u003cbr/\u003e\u003c/span\u003e\n\u003cspan class=\"verse giop_12_3\"\u003e \u003csup\u003e3\u003c/sup\u003e Song ta cũng có sự thông sáng như các ngươi, \u003cbr/\u003e Chẳng kém hơn đâu; mà lại ai là người không biết những việc như thế? \u003cbr/\u003e\u003c/span\u003e\n\u003cspan class=\"verse giop_12_4\"\u003e \u003csup\u003e4\u003c/sup\u003e Ta đã cầu khẩn Đức Chúa Trời, và Đức Chúa Trời đáp lời cho ta; \u003cbr/\u003e Nay ta thành ra trò cười của bầu bạn ta; \u003cbr/\u003e Người công bình, người trọn vẹn đã trở nên một vật chê cười! \u003cbr/\u003e\u003c/span\u003e\n\u003cspan class=\"verse giop_12_5\"\u003e \u003csup\u003e5\u003c/sup\u003e Lòng người nào ở an nhiên khinh bỉ sự tai họa. \u003cbr/\u003e Tai họa thường sẵn giáng trên kẻ nào trợt chân vấp ngã. \u003cbr/\u003e\u003c/span\u003e\n\u003cspan class=\"verse giop_12_6\"\u003e \u003csup\u003e6\u003c/sup\u003e Trại của kẻ cướp được may mắn, \u003cbr/\u003e Những kẻ chọc giận Đức Chúa Trời ở bình an vô sự, \u003cbr/\u003e Và được Đức Chúa Trời phó vào tay mình nhiều tài sản dư dật. \u003cbr/\u003e\u003c/span\u003e\n\u003cspan class=\"verse giop_12_7\"\u003e \u003csup\u003e7\u003c/sup\u003e Nhưng khá hỏi loài thú, chúng nó sẽ dạy dỗ ngươi, \u003cbr/\u003e Hỏi các chim trời, thì chúng nó sẽ bảo cho ngươi; \u003cbr/\u003e\u003c/span\u003e\n\u003cspan class=\"verse giop_12_8\"\u003e \u003csup\u003e8\u003c/sup\u003e Hoặc nữa, hãy nói với đất, nó sẽ giảng dạy cho ngươi; \u003cbr/\u003e Còn những cá biển sẽ thuật rõ cho ngươi biết. \u003cbr/\u003e\u003c/span\u003e\n\u003cspan class=\"verse giop_12_9\"\u003e \u003csup\u003e9\u003c/sup\u003e Trong các loài nầy, loài nào chẳng biết \u003cbr/\u003e Rằng tay của Đức Chúa Trời đã làm ra những vật ấy? \u003cbr/\u003e\u003c/span\u003e\n\u003cspan class=\"verse giop_12_10\"\u003e \u003csup\u003e10\u003c/sup\u003e Trong tay Ngài cầm hồn của mọi vật sống, \u003cbr/\u003e Và hơi thở của cả loài người. \u003cbr/\u003e\u003c/span\u003e\n\u003cspan class=\"verse giop_12_11\"\u003e \u003csup\u003e11\u003c/sup\u003e Lỗ tai há chẳng xét lời nói, \u003cbr/\u003e Như ổ gà nếm những vật thực sao? \u003cbr/\u003e\u003c/span\u003e\n\u003cspan class=\"verse giop_12_12\"\u003e \u003csup\u003e12\u003c/sup\u003e Người già cả có sự khôn ngoan, \u003cbr/\u003e Kẻ hưởng trường thọ được điều thông sáng. \u003cbr/\u003e \u003cbr/\u003e\u003c/span\u003e\n\u003cspan class=\"verse giop_12_13\"\u003e \u003csup\u003e13\u003c/sup\u003e Nơi Đức Chúa Trời có sự khôn ngoan và quyền năng; \u003cbr/\u003e Mưu luận và thông minh đều thuộc về Ngài. \u003cbr/\u003e\u003c/span\u003e\n\u003cspan class=\"verse giop_12_14\"\u003e \u003csup\u003e14\u003c/sup\u003e Kìa, Ngài phá hủy, loài người không cất lại được; \u003cbr/\u003e Ngài giam cầm người nào, không ai mở ra cho. \u003cbr/\u003e\u003c/span\u003e\n\u003cspan class=\"verse giop_12_15\"\u003e \u003csup\u003e15\u003c/sup\u003e Nầy, Ngài ngăn nước lại, nước bèn khô cạn; \u003cbr/\u003e Đoạn, Ngài mở nó ra, nó bèn làm đồi tàn đất, \u003cbr/\u003e\u003c/span\u003e\n\u003cspan class=\"verse giop_12_16\"\u003e \u003csup\u003e16\u003c/sup\u003e Tại nơi Ngài có quyền năng và khôn ngoan; \u003cbr/\u003e Kẻ bị lầm lạc và kẻ làm cho lầm lạc đều thuộc về Ngài. \u003cbr/\u003e\u003c/span\u003e\n\u003cspan class=\"verse giop_12_17\"\u003e \u003csup\u003e17\u003c/sup\u003e Ngài bắt dẫn tù những kẻ bày mưu, \u003cbr/\u003e Khiến các quan xét ra điên dại. \u003cbr/\u003e\u003c/span\u003e\n\u003cspan class=\"verse giop_12_18\"\u003e \u003csup\u003e18\u003c/sup\u003e Ngài mở trói cho các vua, \u003cbr/\u003e Và thắt xiềng xích nơi lưng họ; \u003cbr/\u003e\u003c/span\u003e\n\u003cspan class=\"verse giop_12_19\"\u003e \u003csup\u003e19\u003c/sup\u003e Ngài bắt dẫn tù những thầy tế lễ, \u003cbr/\u003e Đánh đổ các kẻ cường quyền. \u003cbr/\u003e\u003c/span\u003e\n\u003cspan class=\"verse giop_12_20\"\u003e \u003csup\u003e20\u003c/sup\u003e Ngài cất lời khỏi kẻ nói thành tín, \u003cbr/\u003e Làm cho kẻ già cả mất trí khôn. \u003cbr/\u003e\u003c/span\u003e\n\u003cspan class=\"verse giop_12_21\"\u003e \u003csup\u003e21\u003c/sup\u003e Ngài giáng điều sỉ nhục trên kẻ sang trọng, \u003cbr/\u003e Tháo dây lưng của người mạnh bạo. \u003cbr/\u003e\u003c/span\u003e\n\u003cspan class=\"verse giop_12_22\"\u003e \u003csup\u003e22\u003c/sup\u003e Ngài bày tỏ những sự sâu nhiệm ẩn trong tăm tối, \u003cbr/\u003e Và khiến bóng sự chết hóa ra sáng sủa. \u003cbr/\u003e\u003c/span\u003e\n\u003cspan class=\"verse giop_12_23\"\u003e \u003csup\u003e23\u003c/sup\u003e Ngài khiến các dân tộc hưng thịnh, rồi lại phá diệt đi; \u003cbr/\u003e Mở rộng giới hạn cho các nước, đoạn thâu nó lại. \u003cbr/\u003e\u003c/span\u003e\n\u003cspan class=\"verse giop_12_24\"\u003e \u003csup\u003e24\u003c/sup\u003e Ngài cất thông sáng khỏi những trưởng của các dân tộc thế gian, \u003cbr/\u003e Khiến chúng đi dông dài trong đồng vắng không đường lối. \u003cbr/\u003e\u003c/span\u003e\n\u003cspan class=\"verse giop_12_25\"\u003e \u003csup\u003e25\u003c/sup\u003e Chúng rờ đi trong tối tăm, không có sự sáng, \u003cbr/\u003e Và Ngài làm cho họ đi ngả nghiêng như kẻ say. \u003cbr/\u003e\u003c/span\u003e\n"
}